pmtool/AnalysisBox.py
pmtool/DataSet.py
pmtool/FeaturesSet.py
pmtool/GenerateResultBox.py
pmtool/ResultSet.py
pmtool/ToolBox.py
pmtool/__init__.py
precision_medicine_toolbox-0.11.dist-info/LICENSE
precision_medicine_toolbox-0.11.dist-info/METADATA
precision_medicine_toolbox-0.11.dist-info/WHEEL
precision_medicine_toolbox-0.11.dist-info/top_level.txt
precision_medicine_toolbox-0.11.dist-info/RECORD
