Metadata-Version: 2.1
Name: precision-medicine-toolbox
Version: 0.11
Summary: Precision medicine tool-box for medical imaging research
Home-page: https://github.com/primakov/precision-medicine-toolbox
Download-URL: https://github.com/primakov/precision-medicine-toolbox/archive/refs/tags/0.11.tar.gz
Author: sergey primakov & lisa lavrova
Author-email: primakov@bk.ru
License: bsd-3-clause
Keywords: medical imaging research,dicom,radiomics,statistical analysis,features
Classifier: Development Status :: 3 - Alpha
Classifier: Intended Audience :: Developers
Classifier: Topic :: Software Development :: Build Tools
Classifier: License :: OSI Approved :: MIT License
Classifier: Programming Language :: Python :: 3
Classifier: Programming Language :: Python :: 3.6
Classifier: Programming Language :: Python :: 3.7
Classifier: Programming Language :: Python :: 3.8
License-File: LICENSE
Requires-Dist: SimpleITK
Requires-Dist: PyWavelets
Requires-Dist: pykwalify
Requires-Dist: six
Requires-Dist: tqdm
Requires-Dist: pydicom
Requires-Dist: pandas
Requires-Dist: pyradiomics
Requires-Dist: scikit-image
Requires-Dist: ipywidgets
Requires-Dist: matplotlib
Requires-Dist: Pillow
Requires-Dist: scikit-learn
Requires-Dist: scipy
Requires-Dist: plotly
Requires-Dist: mkdocstrings
Requires-Dist: statsmodels
Requires-Dist: opencv-python
Requires-Dist: pickle-mixin
